CG19057UNO/EcuacionesLineales.py
CG19057UNO/EcuacionesNoLineales.py
CG19057UNO/__init__.py
cg19057uno-0.1.0.dist-info/licenses/LICENSE
tests/__init__.py
tests/test_EcuacionesLineales.py
tests/test_EcuacionesNoLineales.py
cg19057uno-0.1.0.dist-info/METADATA
cg19057uno-0.1.0.dist-info/WHEEL
cg19057uno-0.1.0.dist-info/top_level.txt
cg19057uno-0.1.0.dist-info/RECORD
