Metadata-Version: 2.4
Name: CG19057UNO
Version: 0.1.0
Summary: Librería para resolver problemas de ecuaciones lineales y no lineales a través de diferentes métodos numéricos.
Author: Yaquelin Grijalva
Author-email: cg19057@ues.edu.sv
Classifier: Programming Language :: Python :: 3
Classifier: License :: OSI Approved :: MIT License
Classifier: Operating System :: OS Independent
Requires-Python: >=3.6
License-File: LICENSE
Dynamic: author
Dynamic: author-email
Dynamic: classifier
Dynamic: description
Dynamic: description-content-type
Dynamic: license-file
Dynamic: requires-python
Dynamic: summary
